<Root>
  <Meta Author="Morgan" LevelName="Help I'm Stuck in a Video Game!" WelcomeHint="Help I'm Stuck in a Video Game!" Difficulty="Normal" />
  <Grid Width="12" Height="16">
    <Row y="0">
      <Cell x="15" y="0">
        <Button Name="Button+9" Zpos="0">
          <Field Name="colorslot" Type="ColorSlot" Value="Blue" />
        </Button>
      </Cell>
    </Row>
    <Row y="1">
      <Cell x="3" y="1">
        <Teleport Name="teleport+16" Zpos="0">
          <Field Name="targetName" Type="System.String" Value="tile+1" />
          <Field Name="colorslot" Type="ColorSlot" Value="Pink" />
        </Teleport>
      </Cell>
      <Cell x="15" y="1">
        <Block Name="Block+9" Zpos="0">
          <Field Name="colorslot" Type="ColorSlot" Value="Blue" />
        </Block>
      </Cell>
    </Row>
    <Row y="2">
      <Cell x="14" y="2">
        <Tile Name="tile+3" Zpos="0">
          <Field Name="colorslot" Type="ColorSlot" Value="Purple" />
        </Tile>
      </Cell>
    </Row>
    <Row y="3">
      <Cell x="13" y="3">
        <Teleport Name="teleport+17" Zpos="0">
          <Field Name="targetName" Type="System.String" Value="tile+2" />
          <Field Name="colorslot" Type="ColorSlot" Value="Green" />
        </Teleport>
      </Cell>
    </Row>
    <Row y="4">
      <Cell x="0" y="4">
        <Tile Name="tile+4" Zpos="0">
          <Field Name="colorslot" Type="ColorSlot" Value="Blue" />
        </Tile>
      </Cell>
      <Cell x="7" y="4">
        <Teleport Name="teleport+15" Zpos="0">
          <Field Name="targetName" Type="System.String" Value="tile+3" />
          <Field Name="colorslot" Type="ColorSlot" Value="Purple" />
        </Teleport>
      </Cell>
      <Cell x="15" y="4">
        <Switch Name="Switch+48" Zpos="0">
          <Field Name="StartsTriggered" Type="System.Boolean" Value="false" />
          <Field Name="colorslot" Type="ColorSlot" Value="Pink" />
        </Switch>
        <Switch Name="Switch+47" Zpos="1">
          <Field Name="StartsTriggered" Type="System.Boolean" Value="false" />
          <Field Name="colorslot" Type="ColorSlot" Value="Pink" />
        </Switch>
      </Cell>
    </Row>
    <Row y="5">
      <Cell x="4" y="5">
        <Switch Name="Switch+50" Zpos="0">
          <Field Name="StartsTriggered" Type="System.Boolean" Value="false" />
          <Field Name="colorslot" Type="ColorSlot" Value="Green" />
        </Switch>
      </Cell>
      <Cell x="6" y="5">
        <Hint Name="Hint" Zpos="0">
          <Field Name="persistent" Type="System.Boolean" Value="false" />
          <Field Name="oneShot" Type="System.Boolean" Value="false" />
          <Field Name="hint" Type="System.String" Value="Get me outta here!" />
          <Field Name="colorslot" Type="ColorSlot" Value="Blue" />
        </Hint>
      </Cell>
      <Cell x="7" y="5">
        <Player Name="Player" Zpos="0">
          <Field Name="colorslot" Type="ColorSlot" Value="None" />
        </Player>
      </Cell>
    </Row>
    <Row y="7">
      <Cell x="15" y="7">
        <Tile Name="tile+1" Zpos="0">
          <Field Name="colorslot" Type="ColorSlot" Value="Pink" />
        </Tile>
      </Cell>
    </Row>
    <Row y="9">
      <Cell x="0" y="9">
        <End Name="end+11" Zpos="0">
          <Field Name="colorslot" Type="ColorSlot" Value="None" />
        </End>
      </Cell>
      <Cell x="12" y="9">
        <Switch Name="Switch+49" Zpos="0">
          <Field Name="StartsTriggered" Type="System.Boolean" Value="false" />
          <Field Name="colorslot" Type="ColorSlot" Value="Purple" />
        </Switch>
      </Cell>
    </Row>
    <Row y="11">
      <Cell x="5" y="11">
        <Tile Name="tile+2" Zpos="0">
          <Field Name="colorslot" Type="ColorSlot" Value="Green" />
        </Tile>
      </Cell>
      <Cell x="9" y="11">
        <Teleport Name="teleport+14" Zpos="0">
          <Field Name="targetName" Type="System.String" Value="tile+4" />
          <Field Name="colorslot" Type="ColorSlot" Value="Blue" />
        </Teleport>
      </Cell>
    </Row>
  </Grid>
  <Walls>
    <Wall x="0" y="0" Side="bottom" colorslot="None" isTraversible="false" />
    <Wall x="0" y="0" Side="left" colorslot="None" isTraversible="false" />
    <Wall x="1" y="0" Side="bottom" colorslot="None" isTraversible="false" />
    <Wall x="2" y="0" Side="bottom" colorslot="None" isTraversible="false" />
    <Wall x="3" y="0" Side="bottom" colorslot="None" isTraversible="false" />
    <Wall x="4" y="0" Side="bottom" colorslot="None" isTraversible="false" />
    <Door x="4" y="0" Side="left" colorslot="Pink" isTraversible="false" />
    <Wall x="5" y="0" Side="bottom" colorslot="None" isTraversible="false" />
    <Wall x="6" y="0" Side="bottom" colorslot="None" isTraversible="false" />
    <Wall x="7" y="0" Side="bottom" colorslot="None" isTraversible="false" />
    <Wall x="8" y="0" Side="bottom" colorslot="None" isTraversible="false" />
    <Wall x="8" y="0" Side="left" colorslot="None" isTraversible="false" />
    <Wall x="9" y="0" Side="bottom" colorslot="None" isTraversible="false" />
    <Wall x="10" y="0" Side="bottom" colorslot="None" isTraversible="false" />
    <Wall x="10" y="0" Side="left" colorslot="None" isTraversible="false" />
    <Wall x="11" y="0" Side="bottom" colorslot="None" isTraversible="false" />
    <Wall x="12" y="0" Side="bottom" colorslot="None" isTraversible="false" />
    <Wall x="13" y="0" Side="bottom" colorslot="None" isTraversible="false" />
    <Wall x="14" y="0" Side="bottom" colorslot="None" isTraversible="false" />
    <Door x="14" y="0" Side="left" colorslot="Green" isTraversible="false" />
    <Wall x="15" y="0" Side="bottom" colorslot="None" isTraversible="false" />
    <Door x="0" y="1" Side="bottom" colorslot="Pink" isTraversible="false" />
    <Wall x="0" y="1" Side="left" colorslot="None" isTraversible="false" />
    <Wall x="1" y="1" Side="bottom" colorslot="None" isTraversible="false" />
    <Door x="2" y="1" Side="bottom" colorslot="Blue" isTraversible="false" />
    <Wall x="3" y="1" Side="bottom" colorslot="None" isTraversible="false" />
    <Wall x="3" y="1" Side="left" colorslot="None" isTraversible="false" />
    <Wall x="4" y="1" Side="bottom" colorslot="None" isTraversible="false" />
    <Wall x="5" y="1" Side="bottom" colorslot="None" isTraversible="false" />
    <Door x="5" y="1" Side="left" colorslot="Green" isTraversible="false" />
    <Door x="6" y="1" Side="bottom" colorslot="Green" isTraversible="false" />
    <Wall x="7" y="1" Side="bottom" colorslot="None" isTraversible="false" />
    <Door x="8" y="1" Side="bottom" colorslot="Purple" isTraversible="false" />
    <Wall x="8" y="1" Side="left" colorslot="None" isTraversible="false" />
    <Wall x="9" y="1" Side="left" colorslot="None" isTraversible="false" />
    <Wall x="10" y="1" Side="bottom" colorslot="None" isTraversible="false" />
    <Wall x="10" y="1" Side="left" colorslot="None" isTraversible="false" />
    <Door x="11" y="1" Side="bottom" colorslot="Pink" isTraversible="false" />
    <Wall x="12" y="1" Side="bottom" colorslot="None" isTraversible="false" />
    <Wall x="12" y="1" Side="left" colorslot="None" isTraversible="false" />
    <Wall x="13" y="1" Side="bottom" colorslot="None" isTraversible="false" />
    <Wall x="14" y="1" Side="left" colorslot="None" isTraversible="false" />
    <Wall x="0" y="2" Side="left" colorslot="None" isTraversible="false" />
    <Wall x="1" y="2" Side="bottom" colorslot="None" isTraversible="false" />
    <Wall x="1" y="2" Side="left" colorslot="None" isTraversible="false" />
    <Wall x="2" y="2" Side="bottom" colorslot="None" isTraversible="false" />
    <Wall x="3" y="2" Side="left" colorslot="None" isTraversible="false" />
    <Wall x="5" y="2" Side="bottom" colorslot="None" isTraversible="false" />
    <Wall x="5" y="2" Side="left" colorslot="None" isTraversible="false" />
    <Wall x="6" y="2" Side="left" colorslot="None" isTraversible="false" />
    <Wall x="7" y="2" Side="bottom" colorslot="None" isTraversible="false" />
    <Wall x="7" y="2" Side="left" colorslot="None" isTraversible="false" />
    <Wall x="9" y="2" Side="left" colorslot="None" isTraversible="false" />
    <Wall x="10" y="2" Side="left" colorslot="None" isTraversible="false" />
    <Wall x="11" y="2" Side="bottom" colorslot="None" isTraversible="false" />
    <Wall x="11" y="2" Side="left" colorslot="None" isTraversible="false" />
    <Door x="12" y="2" Side="left" colorslot="Green" isTraversible="false" />
    <Wall x="14" y="2" Side="bottom" colorslot="None" isTraversible="false" />
    <Wall x="14" y="2" Side="left" colorslot="None" isTraversible="false" />
    <Wall x="15" y="2" Side="bottom" colorslot="None" isTraversible="false" />
    <Wall x="0" y="3" Side="bottom" colorslot="None" isTraversible="false" />
    <Wall x="0" y="3" Side="left" colorslot="None" isTraversible="false" />
    <Door x="1" y="3" Side="bottom" colorslot="Blue" isTraversible="false" />
    <Wall x="2" y="3" Side="left" colorslot="None" isTraversible="false" />
    <Door x="3" y="3" Side="bottom" colorslot="Blue" isTraversible="false" />
    <Wall x="4" y="3" Side="bottom" colorslot="None" isTraversible="false" />
    <Wall x="4" y="3" Side="left" colorslot="None" isTraversible="false" />
    <Door x="6" y="3" Side="bottom" colorslot="Purple" isTraversible="false" />
    <Wall x="7" y="3" Side="left" colorslot="None" isTraversible="false" />
    <Wall x="8" y="3" Side="bottom" colorslot="None" isTraversible="false" />
    <Wall x="8" y="3" Side="left" colorslot="None" isTraversible="false" />
    <Wall x="9" y="3" Side="bottom" colorslot="None" isTraversible="false" />
    <Wall x="10" y="3" Side="left" colorslot="None" isTraversible="false" />
    <Wall x="11" y="3" Side="left" colorslot="None" isTraversible="false" />
    <Wall x="12" y="3" Side="bottom" colorslot="None" isTraversible="false" />
    <Wall x="13" y="3" Side="bottom" colorslot="None" isTraversible="false" />
    <Wall x="13" y="3" Side="left" colorslot="None" isTraversible="false" />
    <Wall x="14" y="3" Side="bottom" colorslot="None" isTraversible="false" />
    <Wall x="15" y="3" Side="left" colorslot="None" isTraversible="false" />
    <Wall x="0" y="4" Side="bottom" colorslot="None" isTraversible="false" />
    <Wall x="0" y="4" Side="left" colorslot="None" isTraversible="false" />
    <Wall x="1" y="4" Side="left" colorslot="None" isTraversible="false" />
    <Door x="2" y="4" Side="bottom" colorslot="Green" isTraversible="false" />
    <Wall x="2" y="4" Side="left" colorslot="None" isTraversible="false" />
    <Wall x="3" y="4" Side="bottom" colorslot="None" isTraversible="false" />
    <Wall x="4" y="4" Side="bottom" colorslot="None" isTraversible="false" />
    <Wall x="4" y="4" Side="left" colorslot="None" isTraversible="false" />
    <Wall x="5" y="4" Side="bottom" colorslot="None" isTraversible="false" />
    <Wall x="6" y="4" Side="bottom" colorslot="None" isTraversible="false" />
    <Wall x="7" y="4" Side="bottom" colorslot="None" isTraversible="false" />
    <Wall x="8" y="4" Side="left" colorslot="None" isTraversible="false" />
    <Wall x="10" y="4" Side="bottom" colorslot="None" isTraversible="false" />
    <Wall x="10" y="4" Side="left" colorslot="None" isTraversible="false" />
    <Door x="11" y="4" Side="bottom" colorslot="Green" isTraversible="false" />
    <Wall x="11" y="4" Side="left" colorslot="None" isTraversible="false" />
    <Wall x="12" y="4" Side="left" colorslot="None" isTraversible="false" />
    <Wall x="13" y="4" Side="left" colorslot="None" isTraversible="false" />
    <Door x="15" y="4" Side="left" colorslot="Purple" isTraversible="false" />
    <Wall x="0" y="5" Side="left" colorslot="None" isTraversible="false" />
    <Wall x="1" y="5" Side="left" colorslot="None" isTraversible="false" />
    <Wall x="2" y="5" Side="left" colorslot="None" isTraversible="false" />
    <Door x="3" y="5" Side="bottom" colorslot="Blue" isTraversible="false" />
    <Door x="3" y="5" Side="left" colorslot="Pink" isTraversible="false" />
    <Wall x="4" y="5" Side="bottom" colorslot="None" isTraversible="false" />
    <Door x="5" y="5" Side="bottom" colorslot="Pink" isTraversible="false" />
    <Wall x="5" y="5" Side="left" colorslot="None" isTraversible="false" />
    <Wall x="6" y="5" Side="bottom" colorslot="None" isTraversible="false" />
    <Wall x="7" y="5" Side="bottom" colorslot="None" isTraversible="false" />
    <Wall x="8" y="5" Side="bottom" colorslot="None" isTraversible="false" />
    <Wall x="8" y="5" Side="left" colorslot="None" isTraversible="false" />
    <Door x="9" y="5" Side="bottom" colorslot="Purple" isTraversible="false" />
    <Door x="11" y="5" Side="left" colorslot="Purple" isTraversible="false" />
    <Wall x="12" y="5" Side="bottom" colorslot="None" isTraversible="false" />
    <Door x="13" y="5" Side="bottom" colorslot="Green" isTraversible="false" />
    <Wall x="13" y="5" Side="left" colorslot="None" isTraversible="false" />
    <Wall x="14" y="5" Side="bottom" colorslot="None" isTraversible="false" />
    <Wall x="15" y="5" Side="bottom" colorslot="None" isTraversible="false" />
    <Wall x="15" y="5" Side="left" colorslot="None" isTraversible="false" />
    <Wall x="0" y="6" Side="left" colorslot="None" isTraversible="false" />
    <Door x="1" y="6" Side="bottom" colorslot="Purple" isTraversible="false" />
    <Door x="2" y="6" Side="left" colorslot="Green" isTraversible="false" />
    <Wall x="3" y="6" Side="bottom" colorslot="None" isTraversible="false" />
    <Wall x="3" y="6" Side="left" colorslot="None" isTraversible="false" />
    <Wall x="4" y="6" Side="left" colorslot="None" isTraversible="false" />
    <Wall x="5" y="6" Side="bottom" colorslot="None" isTraversible="false" />
    <Wall x="6" y="6" Side="left" colorslot="None" isTraversible="false" />
    <Wall x="7" y="6" Side="bottom" colorslot="None" isTraversible="false" />
    <Wall x="7" y="6" Side="left" colorslot="None" isTraversible="false" />
    <Wall x="8" y="6" Side="bottom" colorslot="None" isTraversible="false" />
    <Wall x="8" y="6" Side="left" colorslot="None" isTraversible="false" />
    <Wall x="9" y="6" Side="bottom" colorslot="None" isTraversible="false" />
    <Wall x="10" y="6" Side="bottom" colorslot="None" isTraversible="false" />
    <Door x="10" y="6" Side="left" colorslot="Purple" isTraversible="false" />
    <Wall x="11" y="6" Side="bottom" colorslot="None" isTraversible="false" />
    <Wall x="12" y="6" Side="left" colorslot="None" isTraversible="false" />
    <Wall x="13" y="6" Side="left" colorslot="None" isTraversible="false" />
    <Wall x="14" y="6" Side="bottom" colorslot="None" isTraversible="false" />
    <Door x="14" y="6" Side="left" colorslot="Green" isTraversible="false" />
    <Door x="0" y="7" Side="bottom" colorslot="Blue" isTraversible="false" />
    <Wall x="0" y="7" Side="left" colorslot="None" isTraversible="false" />
    <Wall x="1" y="7" Side="bottom" colorslot="None" isTraversible="false" />
    <Door x="2" y="7" Side="bottom" colorslot="Blue" isTraversible="false" />
    <Wall x="2" y="7" Side="left" colorslot="None" isTraversible="false" />
    <Wall x="3" y="7" Side="left" colorslot="None" isTraversible="false" />
    <Door x="4" y="7" Side="bottom" colorslot="Green" isTraversible="false" />
    <Wall x="5" y="7" Side="bottom" colorslot="None" isTraversible="false" />
    <Wall x="6" y="7" Side="bottom" colorslot="None" isTraversible="false" />
    <Door x="6" y="7" Side="left" colorslot="Blue" isTraversible="false" />
    <Wall x="8" y="7" Side="bottom" colorslot="None" isTraversible="false" />
    <Door x="9" y="7" Side="left" colorslot="Blue" isTraversible="false" />
    <Wall x="10" y="7" Side="bottom" colorslot="None" isTraversible="false" />
    <Wall x="11" y="7" Side="left" colorslot="None" isTraversible="false" />
    <Wall x="12" y="7" Side="bottom" colorslot="None" isTraversible="false" />
    <Wall x="13" y="7" Side="left" colorslot="None" isTraversible="false" />
    <Wall x="14" y="7" Side="left" colorslot="None" isTraversible="false" />
    <Wall x="15" y="7" Side="bottom" colorslot="None" isTraversible="false" />
    <Wall x="15" y="7" Side="left" colorslot="None" isTraversible="false" />
    <Wall x="0" y="8" Side="left" colorslot="None" isTraversible="false" />
    <Door x="2" y="8" Side="left" colorslot="Blue" isTraversible="false" />
    <Door x="3" y="8" Side="bottom" colorslot="Pink" isTraversible="false" />
    <Wall x="4" y="8" Side="bottom" colorslot="None" isTraversible="false" />
    <Wall x="5" y="8" Side="bottom" colorslot="None" isTraversible="false" />
    <Door x="5" y="8" Side="left" colorslot="Green" isTraversible="false" />
    <Wall x="6" y="8" Side="bottom" colorslot="None" isTraversible="false" />
    <Wall x="7" y="8" Side="bottom" colorslot="None" isTraversible="false" />
    <Wall x="8" y="8" Side="bottom" colorslot="None" isTraversible="false" />
    <Wall x="9" y="8" Side="bottom" colorslot="None" isTraversible="false" />
    <Wall x="9" y="8" Side="left" colorslot="None" isTraversible="false" />
    <Wall x="10" y="8" Side="bottom" colorslot="None" isTraversible="false" />
    <Wall x="11" y="8" Side="bottom" colorslot="None" isTraversible="false" />
    <Wall x="11" y="8" Side="left" colorslot="None" isTraversible="false" />
    <Door x="12" y="8" Side="bottom" colorslot="Blue" isTraversible="false" />
    <Wall x="12" y="8" Side="left" colorslot="None" isTraversible="false" />
    <Wall x="13" y="8" Side="bottom" colorslot="None" isTraversible="false" />
    <Wall x="13" y="8" Side="left" colorslot="None" isTraversible="false" />
    <Wall x="14" y="8" Side="bottom" colorslot="None" isTraversible="false" />
    <Wall x="0" y="9" Side="bottom" colorslot="None" isTraversible="false" />
    <Wall x="0" y="9" Side="left" colorslot="None" isTraversible="false" />
    <Wall x="1" y="9" Side="bottom" colorslot="None" isTraversible="false" />
    <Wall x="1" y="9" Side="left" colorslot="None" isTraversible="false" />
    <Wall x="2" y="9" Side="bottom" colorslot="None" isTraversible="false" />
    <Wall x="3" y="9" Side="bottom" colorslot="None" isTraversible="false" />
    <Wall x="4" y="9" Side="bottom" colorslot="None" isTraversible="false" />
    <Door x="5" y="9" Side="bottom" colorslot="Green" isTraversible="false" />
    <Door x="5" y="9" Side="left" colorslot="Purple" isTraversible="false" />
    <Wall x="6" y="9" Side="bottom" colorslot="None" isTraversible="false" />
    <Wall x="7" y="9" Side="bottom" colorslot="None" isTraversible="false" />
    <Door x="8" y="9" Side="bottom" colorslot="Blue" isTraversible="false" />
    <Wall x="8" y="9" Side="left" colorslot="None" isTraversible="false" />
    <Wall x="10" y="9" Side="bottom" colorslot="None" isTraversible="false" />
    <Wall x="10" y="9" Side="left" colorslot="None" isTraversible="false" />
    <Wall x="12" y="9" Side="left" colorslot="None" isTraversible="false" />
    <Wall x="13" y="9" Side="bottom" colorslot="None" isTraversible="false" />
    <Door x="14" y="9" Side="bottom" colorslot="Green" isTraversible="false" />
    <Wall x="15" y="9" Side="bottom" colorslot="None" isTraversible="false" />
    <Wall x="15" y="9" Side="left" colorslot="None" isTraversible="false" />
    <Wall x="0" y="10" Side="left" colorslot="None" isTraversible="false" />
    <Wall x="1" y="10" Side="bottom" colorslot="None" isTraversible="false" />
    <Wall x="1" y="10" Side="left" colorslot="None" isTraversible="false" />
    <Door x="2" y="10" Side="bottom" colorslot="Purple" isTraversible="false" />
    <Wall x="3" y="10" Side="bottom" colorslot="None" isTraversible="false" />
    <Wall x="4" y="10" Side="bottom" colorslot="None" isTraversible="false" />
    <Wall x="4" y="10" Side="left" colorslot="None" isTraversible="false" />
    <Wall x="5" y="10" Side="bottom" colorslot="None" isTraversible="false" />
    <Door x="6" y="10" Side="bottom" colorslot="Purple" isTraversible="false" />
    <Wall x="6" y="10" Side="left" colorslot="None" isTraversible="false" />
    <Wall x="7" y="10" Side="left" colorslot="None" isTraversible="false" />
    <Wall x="8" y="10" Side="bottom" colorslot="None" isTraversible="false" />
    <Wall x="8" y="10" Side="left" colorslot="None" isTraversible="false" />
    <Door x="9" y="10" Side="bottom" colorslot="Green" isTraversible="false" />
    <Wall x="10" y="10" Side="left" colorslot="None" isTraversible="false" />
    <Wall x="11" y="10" Side="bottom" colorslot="None" isTraversible="false" />
    <Wall x="11" y="10" Side="left" colorslot="None" isTraversible="false" />
    <Door x="12" y="10" Side="bottom" colorslot="Blue" isTraversible="false" />
    <Wall x="13" y="10" Side="bottom" colorslot="None" isTraversible="false" />
    <Wall x="13" y="10" Side="left" colorslot="None" isTraversible="false" />
    <Wall x="14" y="10" Side="bottom" colorslot="None" isTraversible="false" />
    <Door x="14" y="10" Side="left" colorslot="Green" isTraversible="false" />
    <Wall x="0" y="11" Side="left" colorslot="None" isTraversible="false" />
    <Wall x="1" y="11" Side="bottom" colorslot="None" isTraversible="false" />
    <Door x="2" y="11" Side="left" colorslot="Pink" isTraversible="false" />
    <Wall x="3" y="11" Side="bottom" colorslot="None" isTraversible="false" />
    <Wall x="3" y="11" Side="left" colorslot="None" isTraversible="false" />
    <Wall x="5" y="11" Side="bottom" colorslot="None" isTraversible="false" />
    <Wall x="5" y="11" Side="left" colorslot="None" isTraversible="false" />
    <Wall x="7" y="11" Side="bottom" colorslot="None" isTraversible="false" />
    <Door x="8" y="11" Side="left" colorslot="Blue" isTraversible="false" />
    <Door x="10" y="11" Side="bottom" colorslot="Pink" isTraversible="false" />
    <Wall x="10" y="11" Side="left" colorslot="None" isTraversible="false" />
    <Wall x="12" y="11" Side="bottom" colorslot="None" isTraversible="false" />
    <Wall x="12" y="11" Side="left" colorslot="None" isTraversible="false" />
    <Wall x="14" y="11" Side="bottom" colorslot="None" isTraversible="false" />
    <Door x="15" y="11" Side="left" colorslot="Purple" isTraversible="false" />
  </Walls>
</Root>